{
	"configurations" : 
	[
		{
			"directories" : 
			[
				{
					"build" : ".",
					"hasInstallRule" : true,
					"jsonFile" : "directory-.-Debug-c211092ca1ea0834b14a.json",
					"minimumCMakeVersion" : 
					{
						"string" : "3.16"
					},
					"projectIndex" : 0,
					"source" : ".",
					"targetIndexes" : 
					[
						0,
						1,
						2
					]
				}
			],
			"name" : "Debug",
			"projects" : 
			[
				{
					"directoryIndexes" : 
					[
						0
					],
					"name" : "MacroPad",
					"targetIndexes" : 
					[
						0,
						1,
						2
					]
				}
			],
			"targets" : 
			[
				{
					"directoryIndex" : 0,
					"id" : "MacroPad::@6890427a1f51a3e7e1df",
					"jsonFile" : "target-MacroPad-Debug-adc78615f05eaf4c9f6b.json",
					"name" : "MacroPad",
					"projectIndex" : 0
				},
				{
					"directoryIndex" : 0,
					"id" : "MacroPad_autogen::@6890427a1f51a3e7e1df",
					"jsonFile" : "target-MacroPad_autogen-Debug-6286ae705e2ae7a80bd5.json",
					"name" : "MacroPad_autogen",
					"projectIndex" : 0
				},
				{
					"directoryIndex" : 0,
					"id" : "MacroPad_autogen_timestamp_deps::@6890427a1f51a3e7e1df",
					"jsonFile" : "target-MacroPad_autogen_timestamp_deps-Debug-5635446b62c2aa0b9cd0.json",
					"name" : "MacroPad_autogen_timestamp_deps",
					"projectIndex" : 0
				}
			]
		}
	],
	"kind" : "codemodel",
	"paths" : 
	{
		"build" : "C:/Users/aarav/OneDrive/Documents/GitHub/MacroPad/software/build/Desktop_Qt_6_8_2_MinGW_64_bit-Debug",
		"source" : "C:/Users/aarav/OneDrive/Documents/GitHub/MacroPad/software"
	},
	"version" : 
	{
		"major" : 2,
		"minor" : 7
	}
}
